supervisor_gateway/__init__.py
supervisor_gateway/__main__.py
supervisor_gateway/config.py
supervisor_gateway/error.py
supervisor_gateway/event_listener.py
supervisor_gateway/local_state.py
supervisor_gateway/log.py
supervisor_gateway/main.py
supervisor_gateway/schema.py
supervisor_gateway/supervisor.py
supervisor_gateway/time.py
supervisor_gateway/xml_rpc.py
supervisor_gateway/api/__init__.py
supervisor_gateway/api/local.py
supervisor_gateway/api/rpc.py
supervisor_gateway-0.4.0.dist-info/LICENSE
supervisor_gateway-0.4.0.dist-info/METADATA
supervisor_gateway-0.4.0.dist-info/WHEEL
supervisor_gateway-0.4.0.dist-info/top_level.txt
supervisor_gateway-0.4.0.dist-info/RECORD
