Metadata-Version: 2.1
Name: supervisor-gateway
Version: 0.4.0
Summary: An RESTful supervisor gateway with paginated and cached process info
Home-page: https://github.com/ppd0705/supervisor-gateway
Author: ppd0705
Author-email: ppd0705@icloud.com
License: UNKNOWN
Platform: UNKNOWN
Classifier: Intended Audience :: Developers
Classifier: Operating System :: POSIX
Classifier: Programming Language :: Python
Classifier: Programming Language :: Python :: 3
Classifier: Programming Language :: Python :: 3.8
Classifier: Programming Language :: Python :: 3.9
Classifier: Programming Language :: Python :: 3.10
Classifier: Topic :: System :: Boot
Classifier: Topic :: System :: Monitoring
Classifier: Topic :: System :: Systems Administration
Requires-Python: >=3.8
Requires-Dist: aiohttp
Requires-Dist: aiohttp-xmlrpc (>=1.5.0)
Requires-Dist: pydantic
Requires-Dist: starlette
Requires-Dist: fastapi (>=0.75.0)
Requires-Dist: uvicorn (>=0.17.6)
Provides-Extra: lint
Requires-Dist: autoflake (>=1.4.0) ; extra == 'lint'
Requires-Dist: isort (>=5.10.0) ; extra == 'lint'
Requires-Dist: black (>=22.1.0) ; extra == 'lint'
Requires-Dist: flake8 (>=4.0.0) ; extra == 'lint'
Provides-Extra: publish
Requires-Dist: twine (==3.8.0) ; extra == 'publish'
Requires-Dist: wheel (==0.37.1) ; extra == 'publish'
Provides-Extra: test
Requires-Dist: pytest (>=7.1.0) ; extra == 'test'
Requires-Dist: pytest-mock (>=3.7.0) ; extra == 'test'
Requires-Dist: coverage (>=6.3.2) ; extra == 'test'
Requires-Dist: pytest-asyncio (>=0.18.2) ; extra == 'test'
Requires-Dist: httpx (>=0.22.0) ; extra == 'test'
